imongo/__init__.py
imongo/__main__.py
imongo/kernel.py
imongo/style.css
imongo/utils.py
imongo_kernel-0.1.0.dist-info/DESCRIPTION.rst
imongo_kernel-0.1.0.dist-info/METADATA
imongo_kernel-0.1.0.dist-info/RECORD
imongo_kernel-0.1.0.dist-info/WHEEL
imongo_kernel-0.1.0.dist-info/metadata.json
imongo_kernel-0.1.0.dist-info/top_level.txt
