Metadata-Version: 2.0
Name: imongo-kernel
Version: 0.1.0
Summary: A MongoDB kernel for Jupyter
Home-page: https://github.com/gusutabopb/imongo
Author: Gustavo Bezerra
Author-email: gusutabopb@gmail.com
License: MIT
Platform: UNKNOWN
Classifier: Intended Audience :: Developers
Classifier: Intended Audience :: System Administrators
Classifier: Intended Audience :: Science/Research
Classifier: Development Status :: 3 - Alpha
Classifier: Programming Language :: Python :: 3.6
Classifier: Topic :: System :: Shells
Requires-Dist: ipykernel
Requires-Dist: jupyter (>=1.0.0)
Requires-Dist: pexpect (>=4.2.1)
Requires-Dist: pyyaml
